LICENSE
MANIFEST.in
README.md
screenshot.png
setup.cfg
setup.py
imgextract/__init__.py
imgextract/da_icon.png
imgextract/imgext.py
imgextract/imggui.py
imgextract.egg-info/PKG-INFO
imgextract.egg-info/SOURCES.txt
imgextract.egg-info/dependency_links.txt
imgextract.egg-info/requires.txt
imgextract.egg-info/top_level.txt
imgextract/poppler/bin/AUTHORS
imgextract/poppler/bin/BINARIES
imgextract/poppler/bin/COPYING
imgextract/poppler/bin/COPYING3
imgextract/poppler/bin/README
imgextract/poppler/bin/README-XPDF
imgextract/poppler/bin/freetype6.dll
imgextract/poppler/bin/jpeg62.dll
imgextract/poppler/bin/libcairo-2.dll
imgextract/poppler/bin/libexpat-1.dll
imgextract/poppler/bin/libfontconfig-1.dll
imgextract/poppler/bin/libgcc_s_dw2-1.dll
imgextract/poppler/bin/libpixman-1-0.dll
imgextract/poppler/bin/libpng16-16.dll
imgextract/poppler/bin/libpoppler-79.dll
imgextract/poppler/bin/libpoppler-cpp-0.dll
imgextract/poppler/bin/libstdc++-6.dll
imgextract/poppler/bin/libtiff3.dll
imgextract/poppler/bin/pdfdetach.exe
imgextract/poppler/bin/pdffonts.exe
imgextract/poppler/bin/pdfimages.exe
imgextract/poppler/bin/pdfinfo.exe
imgextract/poppler/bin/pdfseparate.exe
imgextract/poppler/bin/pdftocairo.exe
imgextract/poppler/bin/pdftohtml.exe
imgextract/poppler/bin/pdftoppm.exe
imgextract/poppler/bin/pdftops.exe
imgextract/poppler/bin/pdftotext.exe
imgextract/poppler/bin/pdfunite.exe
imgextract/poppler/bin/zlib1.dll