Metadata-Version: 2.1
Name: imgextract
Version: 0.0.1
Summary: A python package for extracting images from PDF/TIF files
Home-page: https://github.com/scionoftech/imgextract
Author: Sai Kumar Yava
Author-email: saikumar.geek@gmail.com
License: MIT
Download-URL: https://github.com/scionoftech/imgextract/releases/tag/imgextract_stable_v0.0.1
Keywords: pdf,tif,tiff,image
Platform: UNKNOWN
Classifier: Development Status :: 5 - Production/Stable
Classifier: Programming Language :: Python
Classifier: Programming Language :: Python :: 3
Classifier: Programming Language :: Python :: 3.5
Classifier: Programming Language :: Python :: 3.6
Classifier: Programming Language :: Python :: 3.7
Classifier: Programming Language :: Python :: Implementation :: CPython
Classifier: Programming Language :: Python :: Implementation :: PyPy
Classifier: License :: OSI Approved :: MIT License
